{
  "widgets": [
    {
      "type": "ScreenPauseWrapper",
      "props": {
        "children": [
          {
            "type": "ScreenPauseOverlayComponent",
            "props": {}
          },
          {
            "type": "AuthScreen",
            "props": {}
          },
          {
            "type": "NavigationScreen",
            "props": {}
          },
          {
            "type": "TabWrapper",
            "props": {
              "children": [
                {
                  "type": "Header",
                  "props": {
                    "companyName": "Addidas",
                    "campaingName": "Kış kampanyası"
                  }
                },
                {
                  "type": "Tab",
                  "props": {
                    "tabs": [
                      {
                        "title": " Product in this Scene",
                        "key": "productInThisScene"
                      },
                      {
                        "title": "All Product",
                        "key": "productsInThisVideo"
                      },
                      {
                        "title": "Suggested Products",
                        "key": "suggestedProduct"
                      },
                      {
                        "title": "Wishlist",
                        "key": "wishList"
                      },
                      {
                        "title": "WatchListScreen",
                        "key": "WatchListScreen"
                      },
                      {
                        "title": "Shopping Cart",
                        "key": "ShoppingCartScreen"
                      }
                    ]
                  }
                },
                {
                  "type": "ProfileScreen",
                  "props": {}
                }
              ]
            }
          },
          {
            "type": "ProductDetailScreen",
            "props": {}
          },
          {
            "type": "AddToWishListScreen",
            "props": {}
          }
        ]
      }
    },
    {
      "type": "ScreenReadyWrapper",
      "props": {
        "children": [
          {
            "type": "ScreenReadyComponent",
            "props": {}
          }
        ]
      }
    },
    {
      "type": "ScreenPlayingWrapper",
      "props": {
        "children": [
          {
            "type": "HotspotScreen",
            "props": {}
          }
        ]
      }
    },
    {
      "type": "ControlBarWrapper",
      "props": {
        "children": [
          {
            "type": "ControlBarScreen",
            "props": {}
          }
        ]
      }
    }
  ]
}
